ut_doa/__init__.py
ut_doa/__version__.py
ut_doa/doa.py
ut_doa/doaod.py
ut_doa/py.typed
ut_doa-2.0.0.20251020.dist-info/licenses/LICENSE.txt
ut_doa-2.0.0.20251020.dist-info/METADATA
ut_doa-2.0.0.20251020.dist-info/WHEEL
ut_doa-2.0.0.20251020.dist-info/top_level.txt
ut_doa-2.0.0.20251020.dist-info/RECORD
